pyjjy/__init__.py
pyjjy/__main__.py
pyjjy/pyjjy.py
pyjjy-0.2.dist-info/LICENSE
pyjjy-0.2.dist-info/METADATA
pyjjy-0.2.dist-info/WHEEL
pyjjy-0.2.dist-info/top_level.txt
pyjjy-0.2.dist-info/RECORD
