Metadata-Version: 2.1
Name: pyjjy
Version: 0.2
Summary: JJY signal emulator using python and pyaudio
Home-page: http://pypi.python.org/pypi/pyjjy/
Author: Haruki EJIRI
Author-email: 0y35.ejiri.vmqewyhw@gmail.com
License: MIT
Platform: UNKNOWN
Classifier: Development Status :: 4 - Beta
Classifier: License :: OSI Approved :: MIT License
Classifier: Programming Language :: Python :: 3
Classifier: Topic :: Home Automation
Classifier: Topic :: Multimedia :: Sound/Audio
Requires-Python: >=3.6
License-File: LICENSE
Requires-Dist: PyAudio (>=0.2.11)
